jtlutil/__init__.py
jtlutil/config.py
jtlutil/datecalc.py
jtlutil/jwtencode.py
jtlutil/py.typed
jtlutil/docker/__init__.py
jtlutil/docker/db.py
jtlutil/docker/manager.py
jtlutil/docker/proc.py
jtlutil/flask/auth.py
jtlutil-0.3.5.dist-info/METADATA
jtlutil-0.3.5.dist-info/WHEEL
jtlutil-0.3.5.dist-info/RECORD
